[
    {
        "image_name": "remove_data/guess/19_54/54_0-54_1.jpg",
        "label": "Subject",
        "score": "1.0"
    },
    {
        "image_name": "remove_data/guess/19_54/54_1-54_2.jpg",
        "label": "Subject",
        "score": "1.0"
    },
    {
        "image_name": "remove_data/guess/19_54/54_2-54_3.jpg",
        "label": "Subject",
        "score": "0.9999994"
    },
    {
        "image_name": "remove_data/guess/19_54/54_3-54_4.jpg",
        "label": "Subject",
        "score": "0.999999"
    },
    {
        "image_name": "remove_data/guess/19_54/54_4-54_5.jpg",
        "label": "Subject",
        "score": "1.0"
    }
]