[
    {
        "image_name": "remove_data/guess/24_61/61_0-61_1.jpg",
        "label": "Subject",
        "score": "0.9999994"
    },
    {
        "image_name": "remove_data/guess/24_61/61_1-61_2.jpg",
        "label": "Subject",
        "score": "0.9999971"
    },
    {
        "image_name": "remove_data/guess/24_61/61_2-61_3.jpg",
        "label": "Subject",
        "score": "0.9999994"
    },
    {
        "image_name": "remove_data/guess/24_61/61_3-61_4.jpg",
        "label": "Subject",
        "score": "1.0"
    },
    {
        "image_name": "remove_data/guess/24_61/61_4-61_5.jpg",
        "label": "Subject",
        "score": "0.99999917"
    }
]