[
    {
        "image_name": "remove_data/guess/27_115/115_0-115_1.jpg",
        "label": "Subject",
        "score": "0.99211335"
    },
    {
        "image_name": "remove_data/guess/27_115/115_1-115_2.jpg",
        "label": "Subject",
        "score": "0.55648106"
    },
    {
        "image_name": "remove_data/guess/27_115/115_2-115_3.jpg",
        "label": "Subject",
        "score": "0.9966958"
    },
    {
        "image_name": "remove_data/guess/27_115/115_3-115_4.jpg",
        "label": "Subject",
        "score": "0.9984216"
    }
]