[
    {
        "image_name": "remove_data/guess/2_111/111_0-111_1.jpg",
        "label": "Subject",
        "score": "0.99983525"
    },
    {
        "image_name": "remove_data/guess/2_111/111_1-111_2.jpg",
        "label": "Subject",
        "score": "0.99982786"
    },
    {
        "image_name": "remove_data/guess/2_111/111_2-111_3.jpg",
        "label": "Subject",
        "score": "0.9999789"
    },
    {
        "image_name": "remove_data/guess/2_111/111_3-111_4.jpg",
        "label": "Subject",
        "score": "0.99999535"
    },
    {
        "image_name": "remove_data/guess/2_111/111_4-111_5.jpg",
        "label": "Subject",
        "score": "0.9988272"
    },
    {
        "image_name": "remove_data/guess/2_111/111_5-111_6.jpg",
        "label": "Subject",
        "score": "0.9996573"
    }
]