[
    {
        "image_name": "remove_data/guess/7_171/171_0-171_1.jpg",
        "label": "Subject",
        "score": "0.30464298"
    },
    {
        "image_name": "remove_data/guess/7_171/171_1-171_2.jpg",
        "label": "Subject",
        "score": "0.9055102"
    },
    {
        "image_name": "remove_data/guess/7_171/171_2-171_3.jpg",
        "label": "Subject",
        "score": "0.6515429"
    },
    {
        "image_name": "remove_data/guess/7_171/171_3-171_4.jpg",
        "label": "Subject",
        "score": "0.804767"
    }
]